LSCDetection/__init__.py
LSCDetection/alignment/__init__.py
LSCDetection/alignment/ci_align.py
LSCDetection/alignment/map_embeddings.py
LSCDetection/alignment/sgns_vi.py
LSCDetection/alignment/sgns_vi_l2normalize.py
LSCDetection/alignment/srv_align.py
LSCDetection/alignment/wi.py
LSCDetection/evaluation/__init__.py
LSCDetection/evaluation/ap.py
LSCDetection/evaluation/spr.py
LSCDetection/measures/__init__.py
LSCDetection/measures/cd.py
LSCDetection/measures/diff.py
LSCDetection/measures/entropy.py
LSCDetection/measures/freq.py
LSCDetection/measures/lnd.py
LSCDetection/measures/rand.py
LSCDetection/measures/trsf.py
LSCDetection/measures/typs.py
LSCDetection/modules/__init__.py
LSCDetection/modules/cupy_utils.py
LSCDetection/modules/embeddings.py
LSCDetection/modules/utils_.py
LSCDetection/postprocessing/__init__.py
LSCDetection/postprocessing/center.py
LSCDetection/postprocessing/pcr.py
LSCDetection/postprocessing/sot.py
LSCDetection/preprocessing/__init__.py
LSCDetection/preprocessing/preprocess.py
LSCDetection/representations/__init__.py
LSCDetection/representations/count.py
LSCDetection/representations/ppmi.py
LSCDetection/representations/ri.py
LSCDetection/representations/sgns.py
LSCDetection/representations/svd.py
LSCDetection/scripts/__init__.py
LSCDetection/testsets/__init__.py
lscdetection_languagechange-0.0.1.dist-info/METADATA
lscdetection_languagechange-0.0.1.dist-info/WHEEL
lscdetection_languagechange-0.0.1.dist-info/top_level.txt
lscdetection_languagechange-0.0.1.dist-info/RECORD
