Metadata-Version: 2.4
Name: LSCDetection-LanguageChange
Version: 0.0.1
Summary: Python Library for LSC Detection
Home-page: https://github.com/pierluigic/LSCDetection
Author: Garrafao
Platform: all
Classifier: Programming Language :: Python :: 3
Classifier: License :: OSI Approved :: MIT License
Classifier: Operating System :: OS Independent
Requires-Python: >=3.8
Requires-Dist: docopt
Dynamic: author
Dynamic: classifier
Dynamic: description-content-type
Dynamic: home-page
Dynamic: platform
Dynamic: requires-dist
Dynamic: requires-python
Dynamic: summary
